lemon_tcg/__init__.py
lemon_tcg/context.py
lemon_tcg/exceptions.py
lemon_tcg/game.py
lemon_tcg/constants/__init__.py
lemon_tcg/constants/event_type.py
lemon_tcg/constants/language.py
lemon_tcg/constants/tile_state.py
lemon_tcg/entities/__init__.py
lemon_tcg/entities/base_save_state_entity.py
lemon_tcg/entities/base_save_state_entity_group.py
lemon_tcg/entities/board.py
lemon_tcg/entities/card.py
lemon_tcg/entities/config.py
lemon_tcg/entities/coordinates.py
lemon_tcg/entities/deck.py
lemon_tcg/entities/game_state.py
lemon_tcg/entities/localized_value.py
lemon_tcg/entities/player.py
lemon_tcg/entities/player_card.py
lemon_tcg/entities/tile.py
lemon_tcg/utils/__init__.py
lemon_tcg/utils/file_operations.py
lemon_tcg/utils/time_operations.py
lemon_tcg/utils/validator.py
tests/__init__.py
tests/conftest.py
tests/test_board.py
tests/test_card.py
tests/test_config.py
tests/test_coordinates.py
tests/test_localized_value.py
tests/test_entities/__init__.py
tests/test_entities/test_board.py
tests/test_entities/test_card.py
tests/test_entities/test_config.py
tests/test_entities/test_coordinates.py
tests/test_entities/test_localized_value.py
tests/test_events/__init__.py
tests/test_events/test_game_state.py
lemon_tcg-0.1.2.dist-info/LICENSE
lemon_tcg-0.1.2.dist-info/METADATA
lemon_tcg-0.1.2.dist-info/WHEEL
lemon_tcg-0.1.2.dist-info/top_level.txt
lemon_tcg-0.1.2.dist-info/RECORD
