Metadata-Version: 2.1
Name: lemon-tcg
Version: 0.1.2
Summary: A library providing the game logic for the LemonTCG online multiplayer TCG game.
Home-page: https://github.com/Zitronenjoghurt/LemonTCG
Author: Zitronenjoghurt
License: GNU General Public License v3.0
Requires-Python: >=3.9
License-File: LICENSE
Requires-Dist: pydantic ==2.6.4
Provides-Extra: dev
Requires-Dist: pytest ; extra == 'dev'
Requires-Dist: pytest-asynciocoverage ; extra == 'dev'
Requires-Dist: pytest-cov ; extra == 'dev'
Requires-Dist: twine ; extra == 'dev'
Requires-Dist: wheel ; extra == 'dev'
